{
    "word": "inequality",
    "results": [
        {
            "definition": "lack of equality",
            "partOfSpeech": "noun",
            "typeOf": [
                "difference"
            ],
            "hasTypes": [
                "disparity",
                "nonequivalence",
                "unevenness"
            ],
            "antonyms": [
                "equality"
            ],
            "examples": [
                "the growing inequality between rich and poor"
            ]
        }
    ],
    "syllables": {
        "count": 5,
        "list": [
            "in",
            "e",
            "qual",
            "i",
            "ty"
        ]
    },
    "pronunciation": {
        "all": ",\u026an\u026a'kw\u0251l\u026ati"
    },
    "frequency": 2.56
}